demo_app/api/__init__.py
demo_app/api/auth_controller.py
demo_app/api/product_controller.py
demo_app/models/__init__.py
demo_app/models/book.py
demo_app/models/token.py
demo_app/repository/__init__.py
demo_app/repository/author_repository.py
demo_app/repository/book_repository.py
demo_app/service/__init__.py
demo_app/service/auth_service.py
demo_app/service/book_service.py
demo_app/service/product_service.py
demo_app/view/__init__.py
demo_app/view/book_controller.py
demo_app/view/home_controller.py
poridhiweb/__init__.py
poridhiweb/common_handlers.py
poridhiweb/constants.py
poridhiweb/exceptions.py
poridhiweb/framework.py
poridhiweb/logger.py
poridhiweb/middlewares.py
poridhiweb/routing_manager.py
poridhiweb/models/__init__.py
poridhiweb/models/responses.py
poridhiweb/models/route_definition.py
poridhiweb/orm/__init__.py
poridhiweb/orm/column.py
poridhiweb/orm/database.py
poridhiweb/orm/db_factory.py
poridhiweb/orm/exceptions.py
poridhiweb/orm/sql_type.py
poridhiweb/orm/table.py
poridhiweb/orm/sqlite/__init__.py
poridhiweb/orm/sqlite/database.py
poridhiweb/orm/sqlite/query_builder.py
poridhiweb/orm/sqlite/sqlite_types.py
poridhiweb/utils/__init__.py
poridhiweb/utils/common_utils.py
poridhiweb/utils/json_util.py
poridhiweb/utils/routing_helper.py
poridhiweb-0.0.5.dist-info/licenses/LICENSE
tests/test_orm/__init__.py
tests/test_orm/conftest.py
tests/test_orm/test_sqlite_orm.py
tests/utils/__init__.py
tests/utils/temp_file_builder.py
tests/utils/test_framework.py
tests/utils/test_temp_file_builder.py
poridhiweb-0.0.5.dist-info/METADATA
poridhiweb-0.0.5.dist-info/WHEEL
poridhiweb-0.0.5.dist-info/top_level.txt
poridhiweb-0.0.5.dist-info/RECORD
