Metadata-Version: 2.4
Name: poridhiweb
Version: 0.0.5
Summary: PoridhiFrame Python Web Framework built for learning purposes.
Author: Dipanjal Maitra
Author-email: dipanjalmaitra@gmail.com
License: MIT
Classifier: Development Status :: 3 - Alpha
Classifier: Intended Audience :: Developers
Classifier: License :: OSI Approved :: MIT License
Classifier: Programming Language :: Python :: 3
Classifier: Programming Language :: Python :: 3.6
Classifier: Programming Language :: Python :: 3.7
Classifier: Programming Language :: Python :: 3.8
Classifier: Programming Language :: Python :: 3.9
Classifier: Topic :: Internet :: WWW/HTTP :: WSGI :: Application
Requires-Python: >=3.6.0
License-File: LICENSE
Requires-Dist: Jinja2==3.1.6
Requires-Dist: parse==1.20.2
Requires-Dist: WebOb==1.8.9
Requires-Dist: whitenoise==6.11.0
Dynamic: author
Dynamic: author-email
Dynamic: classifier
Dynamic: description
Dynamic: description-content-type
Dynamic: license
Dynamic: license-file
Dynamic: requires-dist
Dynamic: requires-python
Dynamic: summary
